{"document":{"id":"0:0","name":"Document","type":"DOCUMENT","children":[{"id":"0:1","name":"Design Tokens","type":"CANVAS","children":[{"id":"3:30","name":"const orange = { orange1: 'hsl(24 70.0% 99.0%)', orange2: 'hsl(24 83.3% 97.6%)', orange3: 'hsl(24 100% 95.3%)', orange4: 'hsl(25 100% 92.2%)', orange5: 'hsl(25 100% 88.2%)', orange6: 'hsl(25 100% 82.8%)', orange7: 'hsl(24 100% 75.3%)', orange8: 'hsl(24 94.5% 64.3%)', orange9: 'hsl(24 94.0% 50.0%)', orange10: 'hsl(24 100% 46.5%)', orange11: 'hsl(24 100% 37.0%)', orange12: 'hsl(15 60.0% 17.0%)', }","type":"TEXT","blendMode":"PASS_THROUGH","absoluteBoundingBox":{"x":-404,"y":-660,"width":177,"height":196},"constraints":{"vertical":"TOP","horizontal":"LEFT"},"fills":[{"blendMode":"NORMAL","type":"SOLID","color":{"r":0,"g":0,"b":0,"a":1}}],"strokes":[],"strokeWeight":1,"strokeAlign":"OUTSIDE","effects":[],"characters":"const orange = {\n  orange1: 'hsl(24 70.0% 99.0%)',\n  orange2: 'hsl(24 83.3% 97.6%)',\n  orange3: 'hsl(24 100% 95.3%)',\n  orange4: 'hsl(25 100% 92.2%)',\n  orange5: 'hsl(25 100% 88.2%)',\n  orange6: 'hsl(25 100% 82.8%)',\n  orange7: 'hsl(24 100% 75.3%)',\n  orange8: 'hsl(24 94.5% 64.3%)',\n  orange9: 'hsl(24 94.0% 50.0%)',\n  orange10: 'hsl(24 100% 46.5%)',\n  orange11: 'hsl(24 100% 37.0%)',\n  orange12: 'hsl(15 60.0% 17.0%)',\n}","style":{"fontFamily":"Roboto","fontPostScriptName":null,"fontWeight":400,"textAutoResize":"WIDTH_AND_HEIGHT","fontSize":12,"textAlignHorizontal":"LEFT","textAlignVertical":"TOP","letterSpacing":0,"lineHeightPx":14.0625,"lineHeightPercent":100,"lineHeightUnit":"INTRINSIC_%"},"layoutVersion":3,"characterStyleOverrides":[],"styleOverrideTable":{},"lineTypes":["NONE","NONE","NONE","NONE","NONE","NONE","NONE","NONE","NONE","NONE","NONE","NONE","NONE","NONE"],"lineIndentations":[0,0,0,0,0,0,0,0,0,0,0,0,0,0]},{"id":"3:32","name":"const green = { green1: 'hsl(136 50.0% 98.9%)', green2: 'hsl(138 62.5% 96.9%)', green3: 'hsl(139 55.2% 94.5%)', green4: 'hsl(140 48.7% 91.0%)', green5: 'hsl(141 43.7% 86.0%)', green6: 'hsl(143 40.3% 79.0%)', green7: 'hsl(146 38.5% 69.0%)', green8: 'hsl(151 40.2% 54.1%)', green9: 'hsl(151 55.0% 41.5%)', green10: 'hsl(152 57.5% 37.6%)', green11: 'hsl(153 67.0% 28.5%)', green12: 'hsl(155 40.0% 14.0%)', }","type":"TEXT","blendMode":"PASS_THROUGH","absoluteBoundingBox":{"x":-713,"y":-691,"width":177,"height":196},"constraints":{"vertical":"TOP","horizontal":"LEFT"},"fills":[{"blendMode":"NORMAL","type":"SOLID","color":{"r":0,"g":0,"b":0,"a":1}}],"strokes":[],"strokeWeight":1,"strokeAlign":"OUTSIDE","effects":[],"characters":"const green = {\n  green1: 'hsl(136 50.0% 98.9%)',\n  green2: 'hsl(138 62.5% 96.9%)',\n  green3: 'hsl(139 55.2% 94.5%)',\n  green4: 'hsl(140 48.7% 91.0%)',\n  green5: 'hsl(141 43.7% 86.0%)',\n  green6: 'hsl(143 40.3% 79.0%)',\n  green7: 'hsl(146 38.5% 69.0%)',\n  green8: 'hsl(151 40.2% 54.1%)',\n  green9: 'hsl(151 55.0% 41.5%)',\n  green10: 'hsl(152 57.5% 37.6%)',\n  green11: 'hsl(153 67.0% 28.5%)',\n  green12: 'hsl(155 40.0% 14.0%)',\n}","style":{"fontFamily":"Roboto","fontPostScriptName":null,"fontWeight":400,"textAutoResize":"WIDTH_AND_HEIGHT","fontSize":12,"textAlignHorizontal":"LEFT","textAlignVertical":"TOP","letterSpacing":0,"lineHeightPx":14.0625,"lineHeightPercent":100,"lineHeightUnit":"INTRINSIC_%"},"layoutVersion":3,"characterStyleOverrides":[],"styleOverrideTable":{},"lineTypes":["NONE","NONE","NONE","NONE","NONE","NONE","NONE","NONE","NONE","NONE","NONE","NONE","NONE","NONE"],"lineIndentations":[0,0,0,0,0,0,0,0,0,0,0,0,0,0]},{"id":"8:2","name":"Colors","type":"FRAME","blendMode":"PASS_THROUGH","children":[{"id":"1:26","name":"Red12","type":"RECTANGLE","blendMode":"PASS_THROUGH","absoluteBoundingBox":{"x":-588,"y":207,"width":52,"height":48},"constraints":{"vertical":"TOP","horizontal":"LEFT"},"fills":[{"blendMode":"NORMAL","type":"SOLID","color":{"r":0.22500000894069672,"g":0.07500000298023224,"b":0.09000004082918167,"a":1}}],"strokes":[],"strokeWeight":1,"strokeAlign":"INSIDE","effects":[]},{"id":"1:2","name":"Blue1","type":"RECTANGLE","blendMode":"PASS_THROUGH","absoluteBoundingBox":{"x":-382,"y":-321,"width":52,"height":48},"constraints":{"vertical":"TOP","horizontal":"LEFT"},"fills":[{"blendMode":"NORMAL","type":"SOLID","color":{"r":0.9839999675750732,"g":0.993066668510437,"b":1,"a":1}}],"strokes":[],"strokeWeight":1,"strokeAlign":"INSIDE","effects":[]},{"id":"1:4","name":"Blue2","type":"RECTANGLE","blendMode":"PASS_THROUGH","absoluteBoundingBox":{"x":-382,"y":-273,"width":52,"height":48},"constraints":{"vertical":"TOP","horizontal":"LEFT"},"fills":[{"blendMode":"NORMAL","type":"SOLID","color":{"r":0.9600000381469727,"g":0.9800000190734863,"b":1,"a":1}}],"strokes":[],"strokeWeight":1,"strokeAlign":"INSIDE","effects":[]},{"id":"1:5","name":"Blue3","type":"RECTANGLE","blendMode":"PASS_THROUGH","absoluteBoundingBox":{"x":-382,"y":-225,"width":52,"height":48},"constraints":{"vertical":"TOP","horizontal":"LEFT"},"fills":[{"blendMode":"NORMAL","type":"SOLID","color":{"r":0.9300000071525574,"g":0.966166615486145,"b":0.9999999403953552,"a":1}}],"strokes":[],"strokeWeight":1,"strokeAlign":"INSIDE","effects":[]},{"id":"1:6","name":"Blue4","type":"RECTANGLE","blendMode":"PASS_THROUGH","absoluteBoundingBox":{"x":-382,"y":-177,"width":52,"height":48},"constraints":{"vertical":"TOP","horizontal":"LEFT"},"fills":[{"blendMode":"NORMAL","type":"SOLID","color":{"r":0.8805999159812927,"g":0.940000057220459,"b":0.9994000792503357,"a":1}}],"strokes":[],"strokeWeight":1,"strokeAlign":"INSIDE","effects":[]},{"id":"1:7","name":"Blue5","type":"RECTANGLE","blendMode":"PASS_THROUGH","absoluteBoundingBox":{"x":-382,"y":-129,"width":52,"height":48},"constraints":{"vertical":"TOP","horizontal":"LEFT"},"fills":[{"blendMode":"NORMAL","type":"SOLID","color":{"r":0.8050000071525574,"g":0.903166651725769,"b":0.9949999451637268,"a":1}}],"strokes":[],"strokeWeight":1,"strokeAlign":"INSIDE","effects":[]},{"id":"1:8","name":"Blue6","type":"RECTANGLE","blendMode":"PASS_THROUGH","absoluteBoundingBox":{"x":-382,"y":-81,"width":52,"height":48},"constraints":{"vertical":"TOP","horizontal":"LEFT"},"fills":[{"blendMode":"NORMAL","type":"SOLID","color":{"r":0.7103999257087708,"g":0.8443199992179871,"b":0.9696000218391418,"a":1}}],"strokes":[],"strokeWeight":1,"strokeAlign":"INSIDE","effects":[]},{"id":"1:9","name":"Blue7","type":"RECTANGLE","blendMode":"PASS_THROUGH","absoluteBoundingBox":{"x":-382,"y":-33,"width":52,"height":48},"constraints":{"vertical":"TOP","horizontal":"LEFT"},"fills":[{"blendMode":"NORMAL","type":"SOLID","color":{"r":0.5928999781608582,"g":0.7818066477775574,"b":0.9470999836921692,"a":1}}],"strokes":[],"strokeWeight":1,"strokeAlign":"INSIDE","effects":[]},{"id":"1:10","name":"Blue8","type":"RECTANGLE","blendMode":"PASS_THROUGH","absoluteBoundingBox":{"x":-382,"y":15,"width":52,"height":48},"constraints":{"vertical":"TOP","horizontal":"LEFT"},"fills":[{"blendMode":"NORMAL","type":"SOLID","color":{"r":0.36299991607666016,"g":0.6882666945457458,"b":0.937000036239624,"a":1}}],"strokes":[],"strokeWeight":1,"strokeAlign":"INSIDE","effects":[]},{"id":"1:11","name":"Blue9","type":"RECTANGLE","blendMode":"PASS_THROUGH","absoluteBoundingBox":{"x":-382,"y":63,"width":52,"height":48},"constraints":{"vertical":"TOP","horizontal":"LEFT"},"fills":[{"blendMode":"NORMAL","type":"SOLID","color":{"r":0,"g":0.5666667222976685,"b":1,"a":1}}],"strokes":[],"strokeWeight":1,"strokeAlign":"INSIDE","effects":[]},{"id":"1:12","name":"Blue10","type":"RECTANGLE","blendMode":"PASS_THROUGH","absoluteBoundingBox":{"x":-382,"y":111,"width":52,"height":48},"constraints":{"vertical":"TOP","horizontal":"LEFT"},"fills":[{"blendMode":"NORMAL","type":"SOLID","color":{"r":0,"g":0.5013332962989807,"b":0.9399999976158142,"a":1}}],"strokes":[],"strokeWeight":1,"strokeAlign":"INSIDE","effects":[]},{"id":"1:13","name":"Blue11","type":"RECTANGLE","blendMode":"PASS_THROUGH","absoluteBoundingBox":{"x":-382,"y":159,"width":52,"height":48},"constraints":{"vertical":"TOP","horizontal":"LEFT"},"fills":[{"blendMode":"NORMAL","type":"SOLID","color":{"r":0,"g":0.4156666696071625,"b":0.8600000143051147,"a":1}}],"strokes":[],"strokeWeight":1,"strokeAlign":"INSIDE","effects":[]},{"id":"1:14","name":"Blue12","type":"RECTANGLE","blendMode":"PASS_THROUGH","absoluteBoundingBox":{"x":-382,"y":207,"width":52,"height":48},"constraints":{"vertical":"TOP","horizontal":"LEFT"},"fills":[{"blendMode":"NORMAL","type":"SOLID","color":{"r":0,"g":0.14500001072883606,"b":0.30000001192092896,"a":1}}],"strokes":[],"strokeWeight":1,"strokeAlign":"INSIDE","effects":[]},{"id":"1:15","name":"Red1","type":"RECTANGLE","blendMode":"PASS_THROUGH","absoluteBoundingBox":{"x":-588,"y":-321,"width":52,"height":48},"constraints":{"vertical":"TOP","horizontal":"LEFT"},"fills":[{"blendMode":"NORMAL","type":"SOLID","color":{"r":1,"g":0.9839999675750732,"b":0.9842666387557983,"a":1}}],"strokes":[],"strokeWeight":1,"strokeAlign":"INSIDE","effects":[]},{"id":"1:16","name":"Red2","type":"RECTANGLE","blendMode":"PASS_THROUGH","absoluteBoundingBox":{"x":-588,"y":-273,"width":52,"height":48},"constraints":{"vertical":"TOP","horizontal":"LEFT"},"fills":[{"blendMode":"NORMAL","type":"SOLID","color":{"r":1,"g":0.9800000190734863,"b":0.9803333282470703,"a":1}}],"strokes":[],"strokeWeight":1,"strokeAlign":"INSIDE","effects":[]},{"id":"1:17","name":"Red3","type":"RECTANGLE","blendMode":"PASS_THROUGH","absoluteBoundingBox":{"x":-588,"y":-225,"width":52,"height":48},"constraints":{"vertical":"TOP","horizontal":"LEFT"},"fills":[{"blendMode":"NORMAL","type":"SOLID","color":{"r":1,"g":0.940000057220459,"b":0.940000057220459,"a":1}}],"strokes":[],"strokeWeight":1,"strokeAlign":"INSIDE","effects":[]},{"id":"1:18","name":"Red4","type":"RECTANGLE","blendMode":"PASS_THROUGH","absoluteBoundingBox":{"x":-588,"y":-177,"width":52,"height":48},"constraints":{"vertical":"TOP","horizontal":"LEFT"},"fills":[{"blendMode":"NORMAL","type":"SOLID","color":{"r":0.999000072479248,"g":0.900999903678894,"b":0.9009999632835388,"a":1}}],"strokes":[],"strokeWeight":1,"strokeAlign":"INSIDE","effects":[]},{"id":"1:19","name":"Red5","type":"RECTANGLE","blendMode":"PASS_THROUGH","absoluteBoundingBox":{"x":-588,"y":-129,"width":52,"height":48},"constraints":{"vertical":"TOP","horizontal":"LEFT"},"fills":[{"blendMode":"NORMAL","type":"SOLID","color":{"r":0.9919999241828918,"g":0.8480001091957092,"b":0.848000168800354,"a":1}}],"strokes":[],"strokeWeight":1,"strokeAlign":"INSIDE","effects":[]},{"id":"1:20","name":"Red6","type":"RECTANGLE","blendMode":"PASS_THROUGH","absoluteBoundingBox":{"x":-588,"y":-81,"width":52,"height":48},"constraints":{"vertical":"TOP","horizontal":"LEFT"},"fills":[{"blendMode":"NORMAL","type":"SOLID","color":{"r":0.9784000515937805,"g":0.7815999388694763,"b":0.7815999984741211,"a":1}}],"strokes":[],"strokeWeight":1,"strokeAlign":"INSIDE","effects":[]},{"id":"1:21","name":"Red7","type":"RECTANGLE","blendMode":"PASS_THROUGH","absoluteBoundingBox":{"x":-588,"y":-33,"width":52,"height":48},"constraints":{"vertical":"TOP","horizontal":"LEFT"},"fills":[{"blendMode":"NORMAL","type":"SOLID","color":{"r":0.9531999230384827,"g":0.6868000626564026,"b":0.6912400126457214,"a":1}}],"strokes":[],"strokeWeight":1,"strokeAlign":"INSIDE","effects":[]},{"id":"1:22","name":"Red8","type":"RECTANGLE","blendMode":"PASS_THROUGH","absoluteBoundingBox":{"x":-588,"y":15,"width":52,"height":48},"constraints":{"vertical":"TOP","horizontal":"LEFT"},"fills":[{"blendMode":"NORMAL","type":"SOLID","color":{"r":0.9220000505447388,"g":0.5579999685287476,"b":0.5640665888786316,"a":1}}],"strokes":[],"strokeWeight":1,"strokeAlign":"INSIDE","effects":[]},{"id":"1:23","name":"Red9","type":"RECTANGLE","blendMode":"PASS_THROUGH","absoluteBoundingBox":{"x":-588,"y":63,"width":52,"height":48},"constraints":{"vertical":"TOP","horizontal":"LEFT"},"fills":[{"blendMode":"NORMAL","type":"SOLID","color":{"r":0.8974999189376831,"g":0.2825000286102295,"b":0.3030000925064087,"a":1}}],"strokes":[],"strokeWeight":1,"strokeAlign":"INSIDE","effects":[]},{"id":"1:24","name":"Red10","type":"RECTANGLE","blendMode":"PASS_THROUGH","absoluteBoundingBox":{"x":-588,"y":111,"width":52,"height":48},"constraints":{"vertical":"TOP","horizontal":"LEFT"},"fills":[{"blendMode":"NORMAL","type":"SOLID","color":{"r":0.8604999780654907,"g":0.2395000457763672,"b":0.2602000832557678,"a":1}}],"strokes":[],"strokeWeight":1,"strokeAlign":"INSIDE","effects":[]},{"id":"1:25","name":"Red11","type":"RECTANGLE","blendMode":"PASS_THROUGH","absoluteBoundingBox":{"x":-588,"y":159,"width":52,"height":48},"constraints":{"vertical":"TOP","horizontal":"LEFT"},"fills":[{"blendMode":"NORMAL","type":"SOLID","color":{"r":0.8084999918937683,"g":0.17150002717971802,"b":0.19273340702056885,"a":1}}],"strokes":[],"strokeWeight":1,"strokeAlign":"INSIDE","effects":[]}],"absoluteBoundingBox":{"x":-728,"y":-336,"width":824,"height":653},"constraints":{"vertical":"TOP","horizontal":"LEFT"},"clipsContent":true,"background":[{"blendMode":"NORMAL","type":"SOLID","color":{"r":1,"g":1,"b":1,"a":1}}],"fills":[{"blendMode":"NORMAL","type":"SOLID","color":{"r":1,"g":1,"b":1,"a":1}}],"strokes":[],"strokeWeight":1,"strokeAlign":"INSIDE","backgroundColor":{"r":1,"g":1,"b":1,"a":1},"effects":[]},{"id":"8:3","name":"Buttons","type":"FRAME","blendMode":"PASS_THROUGH","children":[{"id":"8:8","name":"Button","type":"COMPONENT","blendMode":"PASS_THROUGH","children":[{"id":"8:4","name":"Rectangle 1","type":"RECTANGLE","blendMode":"PASS_THROUGH","absoluteBoundingBox":{"x":126,"y":-699,"width":161,"height":60},"constraints":{"vertical":"SCALE","horizontal":"SCALE"},"fills":[{"blendMode":"NORMAL","type":"SOLID","color":{"r":0,"g":0.5416666865348816,"b":0.08666668087244034,"a":1}}],"strokes":[],"strokeWeight":1,"strokeAlign":"INSIDE","styles":{"fill":"8:20"},"effects":[],"cornerRadius":8},{"id":"8:6","name":"Click here","type":"TEXT","blendMode":"PASS_THROUGH","absoluteBoundingBox":{"x":126,"y":-699,"width":161,"height":60},"constraints":{"vertical":"SCALE","horizontal":"SCALE"},"fills":[{"blendMode":"NORMAL","type":"SOLID","color":{"r":1,"g":1,"b":1,"a":1}}],"strokes":[],"strokeWeight":1,"strokeAlign":"OUTSIDE","styles":{"fill":"8:22"},"effects":[],"characters":"Click here","style":{"fontFamily":"Roboto","fontPostScriptName":null,"fontWeight":400,"fontSize":16,"textAlignHorizontal":"CENTER","textAlignVertical":"CENTER","letterSpacing":0,"lineHeightPx":18.75,"lineHeightPercent":100,"lineHeightUnit":"INTRINSIC_%"},"layoutVersion":3,"characterStyleOverrides":[],"styleOverrideTable":{},"lineTypes":["NONE"],"lineIndentations":[0]}],"absoluteBoundingBox":{"x":126,"y":-699,"width":161,"height":60},"constraints":{"vertical":"CENTER","horizontal":"CENTER"},"clipsContent":false,"background":[{"blendMode":"NORMAL","type":"SOLID","color":{"r":1,"g":1,"b":1,"a":1}}],"fills":[{"blendMode":"NORMAL","type":"SOLID","color":{"r":1,"g":1,"b":1,"a":1}}],"strokes":[],"strokeWeight":1,"strokeAlign":"INSIDE","backgroundColor":{"r":1,"g":1,"b":1,"a":1},"styles":{"fills":"8:22"},"effects":[]}],"absoluteBoundingBox":{"x":96,"y":-732,"width":221,"height":125},"constraints":{"vertical":"TOP","horizontal":"LEFT"},"clipsContent":true,"background":[{"blendMode":"NORMAL","type":"SOLID","color":{"r":1,"g":1,"b":1,"a":1}}],"fills":[{"blendMode":"NORMAL","type":"SOLID","color":{"r":1,"g":1,"b":1,"a":1}}],"strokes":[],"strokeWeight":1,"strokeAlign":"INSIDE","backgroundColor":{"r":1,"g":1,"b":1,"a":1},"effects":[]}],"backgroundColor":{"r":0.8980392217636108,"g":0.8980392217636108,"b":0.8980392217636108,"a":1},"prototypeStartNodeID":null,"flowStartingPoints":[],"prototypeDevice":{"type":"NONE","rotation":"NONE"}}]},"components":{"8:8":{"key":"51432e44fd243896cd3184bce68dcadd8decbfc6","name":"Button","description":"","documentationLinks":[]}},"componentSets":{},"schemaVersion":0,"styles":{"8:20":{"key":"14908ab7079f334bb28700785fa726f618fb7875","name":"Green","styleType":"FILL","description":""},"8:22":{"key":"8c2e1c10acf0af2bd36c759106cbe7e3f5f3ef56","name":"Button text","styleType":"FILL","description":""}},"name":"Mira DS","lastModified":"2022-03-12T06:05:16Z","thumbnailUrl":"https://s3-alpha-sig.figma.com/thumbnails/720cf604-97d6-4141-80fb-0cd4a631cf80?Expires=1648425600&Signature=Q682r1aF0rLzNrtSg6dK~XJEfbCNvSnoKAjVSAzGQeOFBlu7yVoM1-9Y1IiQ2DOMZNm4eA8GvWcyQogtJAB6qKUZSqqnQO~Rf5w4sAP-grbetXhWVuh~5YUMVfoMKjBJCsO11FETRUsqaIcPA7GrvtP-rAaguKjKGQmkLFFkGXN2DPXq0hEub3TU67aRhuAAlQqyTymxOL0Q9FKXmVgHCwgFGqJM15D~A-p5b~NlGPEsFpraBzdAhjo9awSBL1Dii0F5Ja39Pp1CeHyKku6DQvEXo-ogtk1atDJ-2fRXR2JF5eK9rGxzm0Zk6Sc27TwMysSAcqJBYPhuVTtIy51~hw__&Key-Pair-Id=APKAINTVSUGEWH5XD5UA","version":"1644038572","role":"owner","editorType":"figma","linkAccess":"view"}